MANIFEST.in
README.rst
Version
requirements.txt
scheduler.py
setup.py
TaskScheduler.egg-info/PKG-INFO
TaskScheduler.egg-info/SOURCES.txt
TaskScheduler.egg-info/dependency_links.txt
TaskScheduler.egg-info/top_level.txt