Metadata-Version: 1.1
Name: TaskScheduler
Version: 0.0.4
Summary: Scheduler schedules python tasks to run at some delay time later
Home-page: https://github.com/Richard-Mathie/pyScheduler
Author: Richard Mathie
Author-email: richard.mathie@cantab.net
License: MIT
Platform: any
Classifier: Environment :: Web Environment
Classifier: Intended Audience :: Developers
Classifier: License :: OSI Approved :: BSD License
Classifier: Operating System :: OS Independent
Classifier: Programming Language :: Python
Classifier: Programming Language :: Python :: 2
Classifier: Programming Language :: Python :: 2.6
Classifier: Programming Language :: Python :: 2.7
